archive/private_constants08_31.py
archive/tmx_nano2040_wifi_08_31.py
examples/analog_input.py
examples/blink.py
examples/dht.py
examples/digital_in_for_article.py
examples/digital_input_pullup.py
examples/fade.py
examples/hc_sr04.py
examples/i2c_adxl345_accelerometer.py
examples/imu.py
examples/imu2.py
examples/loop_back.py
examples/microphone.py
examples/neopixel_fireworks.py
examples/onewire_ds18x20.py
examples/rgb_blink.py
examples/rgb_fade.py
examples/servo.py
examples/spi_adxl345_accelerometer.py
examples/spi_mpu9250.py
play/chat_client.py
play/rgb_fade.py
tmx_aio_nano2040_wifi/__init__.py
tmx_aio_nano2040_wifi/private_constants.py
tmx_aio_nano2040_wifi/telemetrix_aio.py
tmx_aio_nano2040_wifi/telemetrix_aio_socket.py
tmx_aio_nano2040_wifi/telemtrix_aio_serial.py
tmx_nano2040_wifi/__init__.py
tmx_nano2040_wifi/private_constants.py
tmx_nano2040_wifi/tmx_nano2040_wifi.py
venv/bin/activate_this.py
telemetrix_nano_2040_wifi-1.2.2.dist-info/METADATA
telemetrix_nano_2040_wifi-1.2.2.dist-info/WHEEL
telemetrix_nano_2040_wifi-1.2.2.dist-info/top_level.txt
telemetrix_nano_2040_wifi-1.2.2.dist-info/RECORD
